{
  "matches_expected": true,
  "median_sec": 0.010374972596764565,
  "phases": [
    {
      "candidate_count_pass": 0.0,
      "candidate_download": 7.7465e-05,
      "candidate_write_pass": 0.003110098,
      "emitted_count": 8686,
      "exact_refine": 0.01090472,
      "mode": "count",
      "point_pack": 0.000421445,
      "point_upload": 0.000437854,
      "raw_candidate_count": 8798
    },
    {
      "candidate_count_pass": 0.0,
      "candidate_download": 4.9028e-05,
      "candidate_write_pass": 0.003101016,
      "emitted_count": 8686,
      "exact_refine": 0.006117812,
      "mode": "count",
      "point_pack": 0.000354726,
      "point_upload": 0.000431222,
      "raw_candidate_count": 8798
    },
    {
      "candidate_count_pass": 0.0,
      "candidate_download": 5.615e-05,
      "candidate_write_pass": 0.003125285,
      "emitted_count": 8686,
      "exact_refine": 0.00579567,
      "mode": "count",
      "point_pack": 0.000350349,
      "point_upload": 0.000428514,
      "raw_candidate_count": 8798
    },
    {
      "candidate_count_pass": 0.0,
      "candidate_download": 8.7987e-05,
      "candidate_write_pass": 0.003080364,
      "emitted_count": 8686,
      "exact_refine": 0.005660977,
      "mode": "count",
      "point_pack": 0.000362708,
      "point_upload": 0.00042139,
      "raw_candidate_count": 8798
    },
    {
      "candidate_count_pass": 0.0,
      "candidate_download": 5.9373e-05,
      "candidate_write_pass": 0.003072217,
      "emitted_count": 8686,
      "exact_refine": 0.005585668,
      "mode": "count",
      "point_pack": 0.000340286,
      "point_upload": 0.000420093,
      "raw_candidate_count": 8798
    },
    {
      "candidate_count_pass": 0.0,
      "candidate_download": 5.6125e-05,
      "candidate_write_pass": 0.003087465,
      "emitted_count": 8686,
      "exact_refine": 0.005810449,
      "mode": "count",
      "point_pack": 0.000338474,
      "point_upload": 0.000419222,
      "raw_candidate_count": 8798
    },
    {
      "candidate_count_pass": 0.0,
      "candidate_download": 4.8332e-05,
      "candidate_write_pass": 0.003081433,
      "emitted_count": 8686,
      "exact_refine": 0.005616087,
      "mode": "count",
      "point_pack": 0.000338631,
      "point_upload": 0.000424007,
      "raw_candidate_count": 8798
    }
  ],
  "seconds": [
    0.01567528210580349,
    0.010764740407466888,
    0.010411659255623817,
    0.01028311438858509,
    0.010139143094420433,
    0.010374972596764565,
    0.010178405791521072
  ],
  "value_consistent": true,
  "values": [
    8686,
    8686,
    8686,
    8686,
    8686,
    8686,
    8686
  ]
}