{
  "app": "polygon_pair_overlap_area_rows",
  "backend": "embree",
  "boundary": "Summary mode omits full overlap rows from the JSON payload. Embree still provides native-assisted candidate discovery and CPU/Python exact grid-cell area refinement.",
  "cases": [
    {
      "copies": 64,
      "rows": {
        "backend": "embree",
        "copies": 64,
        "json_bytes_median": 16818,
        "left_polygon_count": 128,
        "max_seconds": 0.02802968496689573,
        "median_seconds": 0.01624734897632152,
        "min_seconds": 0.015842255961615592,
        "output_mode": "rows",
        "repeats": 3,
        "right_polygon_count": 192
      },
      "summary": {
        "backend": "embree",
        "copies": 64,
        "json_bytes_median": 537,
        "json_reduction_vs_rows": 31.318435754189945,
        "left_polygon_count": 128,
        "max_seconds": 0.013207682990469038,
        "median_seconds": 0.012273108994122595,
        "min_seconds": 0.011828474001958966,
        "output_mode": "summary",
        "repeats": 3,
        "right_polygon_count": 192,
        "speedup_vs_rows": 1.3238168897629872
      }
    },
    {
      "copies": 256,
      "rows": {
        "backend": "embree",
        "copies": 256,
        "json_bytes_median": 66404,
        "left_polygon_count": 512,
        "max_seconds": 0.08552057802444324,
        "median_seconds": 0.07828202401287854,
        "min_seconds": 0.07812141801696271,
        "output_mode": "rows",
        "repeats": 3,
        "right_polygon_count": 768
      },
      "summary": {
        "backend": "embree",
        "copies": 256,
        "json_bytes_median": 539,
        "json_reduction_vs_rows": 123.19851576994434,
        "left_polygon_count": 512,
        "max_seconds": 0.05625530198449269,
        "median_seconds": 0.050955077982507646,
        "min_seconds": 0.04446252103662118,
        "output_mode": "summary",
        "repeats": 3,
        "right_polygon_count": 768,
        "speedup_vs_rows": 1.5362948524924631
      }
    },
    {
      "copies": 1024,
      "rows": {
        "backend": "embree",
        "copies": 1024,
        "json_bytes_median": 265419,
        "left_polygon_count": 2048,
        "max_seconds": 0.6553176030283794,
        "median_seconds": 0.6538627470145002,
        "min_seconds": 0.6497143540182151,
        "output_mode": "rows",
        "repeats": 3,
        "right_polygon_count": 3072
      },
      "summary": {
        "backend": "embree",
        "copies": 1024,
        "json_bytes_median": 546,
        "json_reduction_vs_rows": 486.11538461538464,
        "left_polygon_count": 2048,
        "max_seconds": 0.21037158998660743,
        "median_seconds": 0.20554846298182383,
        "min_seconds": 0.19491398299578577,
        "output_mode": "summary",
        "repeats": 3,
        "right_polygon_count": 3072,
        "speedup_vs_rows": 3.181063665128548
      }
    }
  ],
  "goal": 732,
  "measurement": "run_case plus json.dumps wall-clock seconds",
  "repeats": 3
}
