{
  "app": "librts_spatial_index",
  "backend": "optix",
  "box_count": 4096,
  "box_query_prepare_sec": 0.003550715744495392,
  "claim_boundary": {
    "canonical_harness": true,
    "native_engine_customization": false,
    "paper_reproduction_claim_authorized": false,
    "public_speedup_claim_authorized": false,
    "tier_c_no_regression_harness": true,
    "triton_speedup_claim_authorized": false,
    "true_zero_copy_claim_authorized": false,
    "whole_app_speedup_claim_authorized": false
  },
  "cpu_counts": {
    "point_contains": 371793,
    "range_contains": 255739,
    "range_intersects": 553819
  },
  "cpu_reference_sec": 1.786755159497261,
  "elapsed_sec": 0.5190384611487389,
  "fixture": {
    "box_count": 4096,
    "box_query_count": 2048,
    "dataset": "uniform",
    "paper_equivalent_dataset": false,
    "point_query_count": 2048,
    "seed": 2798
  },
  "generic_primitive": "AABB_INDEX_QUERY_2D",
  "goal": "Goal2798",
  "gpu": "NVIDIA RTX 4000 Ada Generation, 565.57.01",
  "harness_version": "rtdl.goal2798.librts_v2_5_warm_median_harness.v1",
  "operations": [
    "point_contains",
    "range_contains",
    "range_intersects"
  ],
  "point_query_prepare_sec": 0.001339241862297058,
  "query_count": 2048,
  "row_count": 3,
  "rows": [
    {
      "expected_count": 371793,
      "generic_primitive": "AABB_INDEX_QUERY_2D",
      "matches_cpu_reference": true,
      "observed_count": 371793,
      "operation": "point_contains",
      "primitive_contract": "generic_prepared_aabb_index_query_2d",
      "query_max_ms": 0.7214024662971497,
      "query_median_ms": 0.7060021162033081,
      "query_min_ms": 0.7036551833152771,
      "query_times_ms": [
        0.7146522402763367,
        0.7214024662971497,
        0.7060021162033081,
        0.7082968950271606,
        0.7148236036300659,
        0.7056593894958496,
        0.7056817412376404,
        0.7036551833152771,
        0.7040128111839294
      ],
      "repeat": 9,
      "rt_core_accelerated": true,
      "status": "pass",
      "warmup": 3
    },
    {
      "expected_count": 255739,
      "generic_primitive": "AABB_INDEX_QUERY_2D",
      "matches_cpu_reference": true,
      "observed_count": 255739,
      "operation": "range_contains",
      "primitive_contract": "generic_prepared_aabb_index_query_2d",
      "query_max_ms": 0.7026791572570801,
      "query_median_ms": 0.6964206695556641,
      "query_min_ms": 0.6951391696929932,
      "query_times_ms": [
        0.6972998380661011,
        0.6958320736885071,
        0.6964206695556641,
        0.695839524269104,
        0.6968602538108826,
        0.7026791572570801,
        0.6987527012825012,
        0.6951391696929932,
        0.6953850388526917
      ],
      "repeat": 9,
      "rt_core_accelerated": true,
      "status": "pass",
      "warmup": 3
    },
    {
      "expected_count": 553819,
      "generic_primitive": "AABB_INDEX_QUERY_2D",
      "matches_cpu_reference": true,
      "observed_count": 553819,
      "operation": "range_intersects",
      "primitive_contract": "generic_prepared_aabb_index_query_2d",
      "query_max_ms": 1.2446492910385132,
      "query_median_ms": 1.2426823377609253,
      "query_min_ms": 1.2414976954460144,
      "query_times_ms": [
        1.241624355316162,
        1.2414976954460144,
        1.2426823377609253,
        1.24301016330719,
        1.2423545122146606,
        1.2437179684638977,
        1.242026686668396,
        1.2446492910385132,
        1.2435540556907654
      ],
      "repeat": 9,
      "rt_core_accelerated": true,
      "status": "pass",
      "warmup": 3
    }
  ],
  "scene_prepare_sec": 0.33893729746341705,
  "seed": 2798,
  "source_commit": "b353be863887fa3b826fc639ea5811d939e93dff",
  "source_dirty": [],
  "status": "pass"
}