{
  "dataset": "clustered3d",
  "grouped_native_tail_mean_sec": 0.0310313175432384,
  "grouped_native_tail_median_sec": 0.031051643542014062,
  "grouped_union_query_block_size": null,
  "min_neighbors": 12,
  "point_count": 32768,
  "prepare_sec": 1.3559902609558776,
  "radius": 0.055,
  "repeat_rows": [
    {
      "core_flag_cache_reused": false,
      "count_native_elapsed_sec": 0.003363983007147908,
      "count_threshold": 12,
      "elapsed_sec": 4.935804919921793,
      "grouped_native_elapsed_sec": 0.4027969059534371,
      "grouped_native_execution_path": "prepared_rt_core_grouped_union_3d_self_query",
      "grouped_native_symbol": "rtdl_optix_apply_prepared_fixed_radius_grouped_union_3d_self_device_outputs",
      "grouped_predicate_mode": null,
      "grouped_query_block_count": null,
      "grouped_query_block_size": null,
      "grouped_query_blocked": null,
      "grouped_query_source": "prepared_search_points_self_query_device",
      "grouped_transfer_mode": "prepared_device_search_points_self_grouped_union_workspaces",
      "neighbor_count_policy": "threshold_capped_at_min_neighbors_not_exact_full_degree",
      "repeat": 1,
      "signature": {
        "cluster_sizes": {
          "1": 8192,
          "2": 8192,
          "3": 8192,
          "4": 8192
        },
        "core_count": 32767,
        "noise_count": 0
      },
      "timing_breakdown": {
        "derived_sec": {
          "adapter_non_native_estimated_sec": 4.516089334967546,
          "count_native_current_run_sec": 0.003363983007147908,
          "elapsed_sec": 4.935804919921793,
          "grouped_native_sec": 0.4027969059534371,
          "known_host_phase_sec": 4.935799671919085,
          "known_native_current_run_sec": 0.406160888960585,
          "unattributed_elapsed_sec": 5.2480027079582214e-06
        },
        "host_observed_sec": {
          "adapter_run_sec": 4.922250223928131,
          "column_signature_sec": 0.013549447990953922
        },
        "notes": [
          "Host-observed timings are diagnostic and may include async GPU synchronization effects.",
          "Native elapsed fields come from RTDL native metadata where available.",
          "This timing packet does not authorize a paper, broad RT-core, or whole-app speedup claim."
        ],
        "performance_claim_authorized": false,
        "schema": "rt_dbscan_grouped_stream_host_overhead_breakdown_v1"
      }
    },
    {
      "core_flag_cache_reused": true,
      "count_native_elapsed_sec": 0.003363983007147908,
      "count_threshold": 12,
      "elapsed_sec": 0.04371018102392554,
      "grouped_native_elapsed_sec": 0.03132902306970209,
      "grouped_native_execution_path": "prepared_rt_core_grouped_union_3d_self_query",
      "grouped_native_symbol": "rtdl_optix_apply_prepared_fixed_radius_grouped_union_3d_self_device_outputs",
      "grouped_predicate_mode": null,
      "grouped_query_block_count": null,
      "grouped_query_block_size": null,
      "grouped_query_blocked": null,
      "grouped_query_source": "prepared_search_points_self_query_device",
      "grouped_transfer_mode": "prepared_device_search_points_self_grouped_union_workspaces",
      "neighbor_count_policy": "threshold_capped_at_min_neighbors_not_exact_full_degree",
      "repeat": 2,
      "signature": {
        "cluster_sizes": {
          "1": 8192,
          "2": 8192,
          "3": 8192,
          "4": 8192
        },
        "core_count": 32767,
        "noise_count": 0
      },
      "timing_breakdown": {
        "derived_sec": {
          "adapter_non_native_estimated_sec": 0.0004024410154670477,
          "count_native_current_run_sec": 0.0,
          "elapsed_sec": 0.04371018102392554,
          "grouped_native_sec": 0.03132902306970209,
          "known_host_phase_sec": 0.04370825015939772,
          "known_native_current_run_sec": 0.03132902306970209,
          "unattributed_elapsed_sec": 1.930864527821541e-06
        },
        "host_observed_sec": {
          "adapter_run_sec": 0.031731464085169137,
          "column_signature_sec": 0.011976786074228585
        },
        "notes": [
          "Host-observed timings are diagnostic and may include async GPU synchronization effects.",
          "Native elapsed fields come from RTDL native metadata where available.",
          "This timing packet does not authorize a paper, broad RT-core, or whole-app speedup claim."
        ],
        "performance_claim_authorized": false,
        "schema": "rt_dbscan_grouped_stream_host_overhead_breakdown_v1"
      }
    },
    {
      "core_flag_cache_reused": true,
      "count_native_elapsed_sec": 0.003363983007147908,
      "count_threshold": 12,
      "elapsed_sec": 0.04333207802847028,
      "grouped_native_elapsed_sec": 0.031172463088296354,
      "grouped_native_execution_path": "prepared_rt_core_grouped_union_3d_self_query",
      "grouped_native_symbol": "rtdl_optix_apply_prepared_fixed_radius_grouped_union_3d_self_device_outputs",
      "grouped_predicate_mode": null,
      "grouped_query_block_count": null,
      "grouped_query_block_size": null,
      "grouped_query_blocked": null,
      "grouped_query_source": "prepared_search_points_self_query_device",
      "grouped_transfer_mode": "prepared_device_search_points_self_grouped_union_workspaces",
      "neighbor_count_policy": "threshold_capped_at_min_neighbors_not_exact_full_degree",
      "repeat": 3,
      "signature": {
        "cluster_sizes": {
          "1": 8192,
          "2": 8192,
          "3": 8192,
          "4": 8192
        },
        "core_count": 32767,
        "noise_count": 0
      },
      "timing_breakdown": {
        "derived_sec": {
          "adapter_non_native_estimated_sec": 0.00024334690533578396,
          "count_native_current_run_sec": 0.0,
          "elapsed_sec": 0.04333207802847028,
          "grouped_native_sec": 0.031172463088296354,
          "known_host_phase_sec": 0.04333057999610901,
          "known_native_current_run_sec": 0.031172463088296354,
          "unattributed_elapsed_sec": 1.4980323612689972e-06
        },
        "host_observed_sec": {
          "adapter_run_sec": 0.03141580999363214,
          "column_signature_sec": 0.011914770002476871
        },
        "notes": [
          "Host-observed timings are diagnostic and may include async GPU synchronization effects.",
          "Native elapsed fields come from RTDL native metadata where available.",
          "This timing packet does not authorize a paper, broad RT-core, or whole-app speedup claim."
        ],
        "performance_claim_authorized": false,
        "schema": "rt_dbscan_grouped_stream_host_overhead_breakdown_v1"
      }
    },
    {
      "core_flag_cache_reused": true,
      "count_native_elapsed_sec": 0.003363983007147908,
      "count_threshold": 12,
      "elapsed_sec": 0.04326806403696537,
      "grouped_native_elapsed_sec": 0.03093082399573177,
      "grouped_native_execution_path": "prepared_rt_core_grouped_union_3d_self_query",
      "grouped_native_symbol": "rtdl_optix_apply_prepared_fixed_radius_grouped_union_3d_self_device_outputs",
      "grouped_predicate_mode": null,
      "grouped_query_block_count": null,
      "grouped_query_block_size": null,
      "grouped_query_blocked": null,
      "grouped_query_source": "prepared_search_points_self_query_device",
      "grouped_transfer_mode": "prepared_device_search_points_self_grouped_union_workspaces",
      "neighbor_count_policy": "threshold_capped_at_min_neighbors_not_exact_full_degree",
      "repeat": 4,
      "signature": {
        "cluster_sizes": {
          "1": 8192,
          "2": 8192,
          "3": 8192,
          "4": 8192
        },
        "core_count": 32767,
        "noise_count": 0
      },
      "timing_breakdown": {
        "derived_sec": {
          "adapter_non_native_estimated_sec": 0.0002126609906554222,
          "count_native_current_run_sec": 0.0,
          "elapsed_sec": 0.04326806403696537,
          "grouped_native_sec": 0.03093082399573177,
          "known_host_phase_sec": 0.0432668779976666,
          "known_native_current_run_sec": 0.03093082399573177,
          "unattributed_elapsed_sec": 1.1860392987728119e-06
        },
        "host_observed_sec": {
          "adapter_run_sec": 0.031143484986387193,
          "column_signature_sec": 0.012123393011279404
        },
        "notes": [
          "Host-observed timings are diagnostic and may include async GPU synchronization effects.",
          "Native elapsed fields come from RTDL native metadata where available.",
          "This timing packet does not authorize a paper, broad RT-core, or whole-app speedup claim."
        ],
        "performance_claim_authorized": false,
        "schema": "rt_dbscan_grouped_stream_host_overhead_breakdown_v1"
      }
    },
    {
      "core_flag_cache_reused": true,
      "count_native_elapsed_sec": 0.003363983007147908,
      "count_threshold": 12,
      "elapsed_sec": 0.043246284942142665,
      "grouped_native_elapsed_sec": 0.030692960019223392,
      "grouped_native_execution_path": "prepared_rt_core_grouped_union_3d_self_query",
      "grouped_native_symbol": "rtdl_optix_apply_prepared_fixed_radius_grouped_union_3d_self_device_outputs",
      "grouped_predicate_mode": null,
      "grouped_query_block_count": null,
      "grouped_query_block_size": null,
      "grouped_query_blocked": null,
      "grouped_query_source": "prepared_search_points_self_query_device",
      "grouped_transfer_mode": "prepared_device_search_points_self_grouped_union_workspaces",
      "neighbor_count_policy": "threshold_capped_at_min_neighbors_not_exact_full_degree",
      "repeat": 5,
      "signature": {
        "cluster_sizes": {
          "1": 8192,
          "2": 8192,
          "3": 8192,
          "4": 8192
        },
        "core_count": 32767,
        "noise_count": 0
      },
      "timing_breakdown": {
        "derived_sec": {
          "adapter_non_native_estimated_sec": 0.0002224069321528077,
          "count_native_current_run_sec": 0.0,
          "elapsed_sec": 0.043246284942142665,
          "grouped_native_sec": 0.030692960019223392,
          "known_host_phase_sec": 0.043244821950793266,
          "known_native_current_run_sec": 0.030692960019223392,
          "unattributed_elapsed_sec": 1.4629913493990898e-06
        },
        "host_observed_sec": {
          "adapter_run_sec": 0.0309153669513762,
          "column_signature_sec": 0.012329454999417067
        },
        "notes": [
          "Host-observed timings are diagnostic and may include async GPU synchronization effects.",
          "Native elapsed fields come from RTDL native metadata where available.",
          "This timing packet does not authorize a paper, broad RT-core, or whole-app speedup claim."
        ],
        "performance_claim_authorized": false,
        "schema": "rt_dbscan_grouped_stream_host_overhead_breakdown_v1"
      }
    }
  ],
  "signature_mode": "column",
  "signatures_match": true,
  "tail_mean_sec": 0.043389152007875964,
  "tail_median_sec": 0.043300071032717824,
  "tail_timing_breakdown_median_sec": {
    "derived": {
      "adapter_non_native_estimated_sec": 0.00023287691874429584,
      "count_native_current_run_sec": 0.0,
      "grouped_native_sec": 0.031051643542014062,
      "known_native_current_run_sec": 0.031051643542014062,
      "unattributed_elapsed_sec": 1.4805118553340435e-06
    },
    "host_observed": {
      "adapter_run_sec": 0.031279647490009665,
      "column_signature_sec": 0.012050089542753994
    },
    "schema": "rt_dbscan_grouped_stream_host_overhead_breakdown_v1"
  }
}